fast_curator/__init__.py
fast_curator/__main__.py
fast_curator/read.py
fast_curator/version.py
fast_curator/write.py
fast_curator/catalogues/__init__.py
fast_curator/catalogues/cms_das.py
fast_curator/catalogues/common.py
fast_curator-0.8.1.dist-info/LICENSE
fast_curator-0.8.1.dist-info/METADATA
fast_curator-0.8.1.dist-info/WHEEL
fast_curator-0.8.1.dist-info/entry_points.txt
fast_curator-0.8.1.dist-info/top_level.txt
fast_curator-0.8.1.dist-info/zip-safe
fast_curator-0.8.1.dist-info/RECORD
