Metadata-Version: 2.1
Name: fast-curator
Version: 0.8.1
Summary: F.A.S.T. package for describing datasets
Home-page: https://github.com/FAST-HEP/fast-curator
Author: F.A.S.T
Author-email: fast-hep@cern.ch
License: Apache Software License 2.0
Keywords: ROOT,analysis,particle physics,HEP,F.A.S.T
Platform: UNKNOWN
Classifier: Development Status :: 4 - Beta
Classifier: Intended Audience :: Developers
Classifier: License :: OSI Approved :: Apache Software License
Classifier: Natural Language :: English
Classifier: Programming Language :: Python :: 3
Classifier: Programming Language :: Python :: 3.7
Classifier: Programming Language :: Python :: 3.8
License-File: LICENSE
Requires-Dist: pyyaml
Requires-Dist: six
Requires-Dist: uproot (>=4.0.7)
Requires-Dist: uproot3
